Metadata-Version: 1.0
Name: bmi-calc-new
Version: 0.2
Summary: Calculate Body mas Index
Home-page: UNKNOWN
Author: UNKNOWN
Author-email: UNKNOWN
License: UNKNOWN
Platform: UNKNOWN
